runtm_shared/__init__.py
runtm_shared/deploy_tracking.py
runtm_shared/discovery.py
runtm_shared/env.py
runtm_shared/errors.py
runtm_shared/ids.py
runtm_shared/lockfiles.py
runtm_shared/manifest.py
runtm_shared/redis.py
runtm_shared/requests.py
runtm_shared/types.py
runtm_shared/urls.py
runtm_shared/dns/__init__.py
runtm_shared/dns/base.py
runtm_shared/dns/cloudflare.py
runtm_shared/storage/__init__.py
runtm_shared/storage/base.py
runtm_shared/telemetry/__init__.py
runtm_shared/telemetry/base.py
runtm_shared/telemetry/exporter.py
runtm_shared/telemetry/identity.py
runtm_shared/telemetry/metrics.py
runtm_shared/telemetry/providers.py
runtm_shared/telemetry/service.py
runtm_shared/telemetry/spans.py
runtm_shared/telemetry/spool.py
runtm_shared-0.2.2.dist-info/METADATA
runtm_shared-0.2.2.dist-info/WHEEL
runtm_shared-0.2.2.dist-info/licenses/LICENSE
runtm_shared-0.2.2.dist-info/RECORD
